symbolserver/__init__.py
symbolserver/test/__init__.py
symbolserver/test/profiles/bctest.py
symbolserver/test/profiles/bctest.py.bc
symbolserver/test/profiles/example.jitlog
symbolserver/test/profiles/example.py
symbolserver/test/profiles/pypy-pystone.prof.jit
symbolserver/test/test_symbolserver.py
vmprof_firefox_converter-0.1.2.dist-info/METADATA
vmprof_firefox_converter-0.1.2.dist-info/WHEEL
vmprof_firefox_converter-0.1.2.dist-info/entry_points.txt
vmprof_firefox_converter-0.1.2.dist-info/licenses/LICENSE
vmprofconvert/__init__.py
vmprofconvert/__main__.py
vmprofconvert/geckoformat.py
vmprofconvert/processedformat.py
vmprofconvert/pypylog.py
vmprofconvert/test/__init__.py
vmprofconvert/test/gecko_example.json
vmprofconvert/test/processed_example.json
vmprofconvert/test/processed_example_with_mem.json
vmprofconvert/test/profiles.json
vmprofconvert/test/profiles/cpuburn.cpython.tsprof
vmprofconvert/test/profiles/dummy.json
vmprofconvert/test/profiles/example.json
vmprofconvert/test/profiles/example.prof
vmprofconvert/test/profiles/example.py
vmprofconvert/test/profiles/example_with_lines.prof
vmprofconvert/test/profiles/example_with_lines.prof.json
vmprofconvert/test/profiles/multithread_example.prof
vmprofconvert/test/profiles/multithread_example.prof.json
vmprofconvert/test/profiles/pypy-pystone.json
vmprofconvert/test/profiles/pypy-pystone.prof
vmprofconvert/test/profiles/pypy-pystone.prof.jit
vmprofconvert/test/profiles/pystone.pypylog
vmprofconvert/test/profiles/vmprof_cpuburn.json
vmprofconvert/test/profiles/vmprof_cpuburn.prof
vmprofconvert/test/test_convert.py
vmprof_firefox_converter-0.1.2.dist-info/RECORD
