Metadata-Version: 2.1
Name: vmprof-firefox-converter
Version: 0.1.2
Summary: Firefox-Profiler as UI for VMProf
Author: Christoph Jung
License: MIT
Requires-Python: <3.12,>=3.9
Requires-Dist: vmprof
Requires-Dist: flask
Requires-Dist: flask-cors
